Metadata-Version: 2.1
Name: auxiliary-distributions
Version: 1.0
Summary: Gaussian and Binomial distributions
